[
    {
        "id": 6,
        "firstName": "Stewart",
        "lastName": "Koelpin",
        "email": "Stewart.Koelpin@hotmail.com",
        "phone": "+1 772564-5880"
    },
    {
        "id": 7,
        "firstName": "Kelly",
        "lastName": "Brakus",
        "email": "Kelly44@gmail.com",
        "phone": "+1 348978-3752"
    },
    {
        "id": 8,
        "firstName": "Darlene",
        "lastName": "Lehner",
        "email": "Darlene.Lehner@hotmail.com",
        "phone": "+1 611536-6125"
    },
    {
        "id": 9,
        "firstName": "Judy",
        "lastName": "Ritchie",
        "email": "Judy54@yahoo.com",
        "phone": "+1 044529-2668"
    },
    {
        "id": 10,
        "firstName": "Cristina",
        "lastName": "Rohan",
        "email": "Cristina.Rohan@gmail.com",
        "phone": "+1 134570-8898"
    },
    {
        "id": 11,
        "firstName": "Billy",
        "lastName": "Kertzmann",
        "email": "Billy_Kertzmann@gmail.com",
        "phone": "+1 039954-8938"
    },
    {
        "id": 12,
        "firstName": "Lori",
        "lastName": "Ruecker",
        "email": "Lori_Ruecker70@yahoo.com",
        "phone": "+1 353836-4445"
    },
    {
        "id": 13,
        "firstName": "Kathy",
        "lastName": "Schroeder",
        "email": "Kathy19@yahoo.com",
        "phone": "+1 804202-4290"
    },
    {
        "id": 14,
        "firstName": "Jane",
        "lastName": "Littel",
        "email": "Jane.Littel48@gmail.com",
        "phone": "+1 923660-6584"
    },
    {
        "id": 15,
        "firstName": "Elena",
        "lastName": "Romaguera",
        "email": "Elena_Romaguera@gmail.com",
        "phone": "+1 280745-5729"
    },
    {
        "id": 16,
        "firstName": "Derek",
        "lastName": "Armstrong",
        "email": "Derek.Armstrong@gmail.com",
        "phone": "+1 686250-7771"
    },
    {
        "id": 17,
        "firstName": "Tracy",
        "lastName": "Nicolas",
        "email": "Tracy65@hotmail.com",
        "phone": "+1 995361-3581"
    },
    {
        "id": 18,
        "firstName": "Natasha",
        "lastName": "Harvey",
        "email": "Natasha41@yahoo.com",
        "phone": "+1 142091-7054"
    },
    {
        "id": 19,
        "firstName": "Rita",
        "lastName": "Heller",
        "email": "Rita16@yahoo.com",
        "phone": "+1 854515-0892"
    },
    {
        "id": 20,
        "firstName": "Sheryl",
        "lastName": "Fritsch",
        "email": "Sheryl_Fritsch55@gmail.com",
        "phone": "+1 361230-1484"
    },
    {
        "id": 21,
        "firstName": "Cristina",
        "lastName": "Wiegand",
        "email": "Antoinette_Wiegand7@gmail.com",
        "phone": "+1 926305-6597"
    },
    {
        "id": 22,
        "firstName": "Mabel",
        "lastName": "Bradtke",
        "email": "Mabel43@yahoo.com",
        "phone": "+1 361866-8631"
    },
    {
        "id": 23,
        "firstName": "Ross",
        "lastName": "Bradtke",
        "email": "Ross_Bradtke58@hotmail.com",
        "phone": "+1 847502-0246"
    },
    {
        "id": 24,
        "firstName": "Alejandro",
        "lastName": "Hane",
        "email": "Alejandro.Hane6@hotmail.com",
        "phone": "+1 600654-1880"
    },
    {
        "id": 25,
        "firstName": "Courtney",
        "lastName": "Fritsch",
        "email": "Courtney.Fritsch12@gmail.com",
        "phone": "+1 852666-6573"
    },
    {
        "id": 26,
        "firstName": "Erin",
        "lastName": "Purdy",
        "email": "Erin9@yahoo.com",
        "phone": "+1 178367-3659"
    },
    {
        "id": 27,
        "firstName": "Judy",
        "lastName": "Reichel",
        "email": "Judy.Reichel54@gmail.com",
        "phone": "+1 950108-3828"
    },
    {
        "id": 28,
        "firstName": "Ben",
        "lastName": "Tremblay",
        "email": "Ben_Tremblay@gmail.com",
        "phone": "+1 747278-2614"
    },
    {
        "id": 29,
        "firstName": "Angel",
        "lastName": "Nader",
        "email": "Angel_Nader39@hotmail.com",
        "phone": "+1 009482-2089"
    },
    {
        "id": 30,
        "firstName": "Francisco",
        "lastName": "Blick",
        "email": "Francisco74@gmail.com",
        "phone": "+1 568851-3782"
    },
    {
        "id": 31,
        "firstName": "Rosalie",
        "lastName": "Ferry",
        "email": "Rosalie_Ferry@yahoo.com",
        "phone": "+1 207386-6868"
    },
    {
        "id": 32,
        "firstName": "Deanna",
        "lastName": "Deckow",
        "email": "Deanna.Deckow63@gmail.com",
        "phone": "+1 056310-6026"
    },
    {
        "id": 33,
        "firstName": "Cristina",
        "lastName": "Schmeler",
        "email": "Aubrey_Schmeler@yahoo.com",
        "phone": "+1 750476-5521"
    },
    {
        "id": 34,
        "firstName": "Renee",
        "lastName": "Raynor",
        "email": "Renee_Raynor@gmail.com",
        "phone": "+1 456571-6092"
    },
    {
        "id": 35,
        "firstName": "Connie",
        "lastName": "Ryan",
        "email": "Connie_Ryan9@yahoo.com",
        "phone": "+1 037526-5563"
    },
    {
        "id": 36,
        "firstName": "Francis",
        "lastName": "Borer",
        "email": "Francis7@yahoo.com",
        "phone": "+1 015519-3848"
    },
    {
        "id": 37,
        "firstName": "Dan",
        "lastName": "Keebler-Grady",
        "email": "Dan68@gmail.com",
        "phone": "+1 292214-4029"
    },
    {
        "id": 38,
        "firstName": "Leroy",
        "lastName": "Ondricka",
        "email": "Leroy.Ondricka@gmail.com",
        "phone": "+1 405592-6955"
    },
    {
        "id": 39,
        "firstName": "Casey",
        "lastName": "Cummings",
        "email": "Casey_Cummings@yahoo.com",
        "phone": "+1 151030-9334"
    },
    {
        "id": 40,
        "firstName": "Merle",
        "lastName": "Feeney",
        "email": "Merle_Feeney93@gmail.com",
        "phone": "+1 494389-9098"
    },
    {
        "id": 41,
        "firstName": "Victor",
        "lastName": "Hyatt",
        "email": "Victor67@gmail.com",
        "phone": "+1 318683-0826"
    },
    {
        "id": 42,
        "firstName": "Nelson",
        "lastName": "Emmerich",
        "email": "Nelson.Emmerich@gmail.com",
        "phone": "+1 715742-5039"
    },
    {
        "id": 43,
        "firstName": "Susie",
        "lastName": "Wehner",
        "email": "Susie49@yahoo.com",
        "phone": "+1 035907-4509"
    },
    {
        "id": 44,
        "firstName": "Robin",
        "lastName": "Collins",
        "email": "Robin.Collins@gmail.com",
        "phone": "+1 835252-4105"
    },
    {
        "id": 45,
        "firstName": "Steve",
        "lastName": "Pollich",
        "email": "Steve.Pollich30@hotmail.com",
        "phone": "+1 901743-2333"
    },
    {
        "id": 46,
        "firstName": "Eleanor",
        "lastName": "Kunde",
        "email": "Eleanor.Kunde84@gmail.com",
        "phone": "+1 555215-0543"
    },
    {
        "id": 47,
        "firstName": "Sue",
        "lastName": "Windler",
        "email": "Sue_Windler72@gmail.com",
        "phone": "+1 313206-5598"
    },
    {
        "id": 48,
        "firstName": "Pat",
        "lastName": "Corwin",
        "email": "Pat_Corwin25@hotmail.com",
        "phone": "+1 317490-8451"
    },
    {
        "id": 49,
        "firstName": "Angel",
        "lastName": "Pacocha",
        "email": "Angel5@gmail.com",
        "phone": "+1 473481-1508"
    },
    {
        "id": 50,
        "firstName": "Roland",
        "lastName": "Braun",
        "email": "Roland94@gmail.com",
        "phone": "+1 139767-1485"
    },
    {
        "id": 51,
        "firstName": "Jeffery",
        "lastName": "Haag",
        "email": "Jeffery.Haag0@gmail.com",
        "phone": "+1 633781-1637"
    },
    {
        "id": 52,
        "firstName": "Ernest",
        "lastName": "Nolan",
        "email": "Ernest.Nolan69@gmail.com",
        "phone": "+1 105691-4204"
    },
    {
        "id": 53,
        "firstName": "Otis",
        "lastName": "Klocko",
        "email": "Otis50@yahoo.com",
        "phone": "+1 111801-8407"
    },
    {
        "id": 54,
        "firstName": "Jamie",
        "lastName": "Hand-Sanford",
        "email": "Jamie_Hand-Sanford@yahoo.com",
        "phone": "+1 384064-4507"
    },
    {
        "id": 55,
        "firstName": "Curtis",
        "lastName": "Konopelski",
        "email": "Curtis_Konopelski@gmail.com",
        "phone": "+1 584866-9005"
    },
    {
        "id": 56,
        "firstName": "Lucas",
        "lastName": "Stracke",
        "email": "Lucas.Stracke37@hotmail.com",
        "phone": "+1 285430-5491"
    },
    {
        "id": 57,
        "firstName": "Amber",
        "lastName": "Kuhlman",
        "email": "Amber_Kuhlman@yahoo.com",
        "phone": "+1 170653-3928"
    },
    {
        "id": 58,
        "firstName": "Kim",
        "lastName": "Crist",
        "email": "Kim_Crist@gmail.com",
        "phone": "+1 301562-4566"
    },
    {
        "id": 59,
        "firstName": "Marshall",
        "lastName": "Mosciski",
        "email": "Marshall74@hotmail.com",
        "phone": "+1 854354-8972"
    },
    {
        "id": 60,
        "firstName": "Helen",
        "lastName": "Bernier",
        "email": "Helen.Bernier@yahoo.com",
        "phone": "+1 980507-9981"
    },
    {
        "id": 61,
        "firstName": "Vera",
        "lastName": "Ondricka",
        "email": "Vera_Ondricka53@yahoo.com",
        "phone": "+1 508806-2931"
    },
    {
        "id": 62,
        "firstName": "Sidney",
        "lastName": "Tromp",
        "email": "Sidney.Tromp@yahoo.com",
        "phone": "+1 037735-4162"
    },
    {
        "id": 63,
        "firstName": "Terry",
        "lastName": "Koch",
        "email": "Terry28@gmail.com",
        "phone": "+1 749087-6100"
    },
    {
        "id": 64,
        "firstName": "Anne",
        "lastName": "McCullough-Reichert",
        "email": "Anne.McCullough-Reichert@gmail.com",
        "phone": "+1 439768-4045"
    },
    {
        "id": 65,
        "firstName": "Andres",
        "lastName": "Rath",
        "email": "Andres.Rath@hotmail.com",
        "phone": "+1 071205-0505"
    },
    {
        "id": 66,
        "firstName": "Ted",
        "lastName": "Berge",
        "email": "Ted72@hotmail.com",
        "phone": "+1 735969-1931"
    },
    {
        "id": 67,
        "firstName": "Kerry",
        "lastName": "Will",
        "email": "Kerry_Will60@gmail.com",
        "phone": "+1 969449-5542"
    },
    {
        "id": 68,
        "firstName": "Jeanne",
        "lastName": "Howell",
        "email": "Jeanne_Howell@yahoo.com",
        "phone": "+1 109074-4342"
    },
    {
        "id": 69,
        "firstName": "Yvette",
        "lastName": "Mertz",
        "email": "Yvette96@hotmail.com",
        "phone": "+1 523102-3896"
    },
    {
        "id": 70,
        "firstName": "Glen",
        "lastName": "McLaughlin",
        "email": "Glen_McLaughlin@yahoo.com",
        "phone": "+1 960706-4921"
    },
    {
        "id": 71,
        "firstName": "Ella",
        "lastName": "Bednar",
        "email": "Ella.Bednar@yahoo.com",
        "phone": "+1 832763-2158"
    },
    {
        "id": 72,
        "firstName": "Sylvester",
        "lastName": "Krajcik",
        "email": "Sylvester_Krajcik@yahoo.com",
        "phone": "+1 169489-3738"
    },
    {
        "id": 73,
        "firstName": "Gina",
        "lastName": "Rolfson",
        "email": "Gina.Rolfson@hotmail.com",
        "phone": "+1 319970-8971"
    },
    {
        "id": 74,
        "firstName": "Marian",
        "lastName": "Bins",
        "email": "Marian_Bins71@hotmail.com",
        "phone": "+1 731936-6286"
    },
    {
        "id": 75,
        "firstName": "Myra",
        "lastName": "Homenick",
        "email": "Myra_Homenick@gmail.com",
        "phone": "+1 606556-2004"
    },
    {
        "id": 76,
        "firstName": "Roberta",
        "lastName": "Cronin",
        "email": "Roberta_Cronin@yahoo.com",
        "phone": "+1 459281-3535"
    },
    {
        "id": 77,
        "firstName": "Sidney",
        "lastName": "Senger",
        "email": "Sidney95@yahoo.com",
        "phone": "+1 032803-8222"
    },
    {
        "id": 78,
        "firstName": "Sue",
        "lastName": "Lindgren",
        "email": "Sue65@hotmail.com",
        "phone": "+1 229227-8634"
    },
    {
        "id": 79,
        "firstName": "Verna",
        "lastName": "Connelly",
        "email": "Verna_Connelly@hotmail.com",
        "phone": "+1 516992-0829"
    },
    {
        "id": 80,
        "firstName": "Juana",
        "lastName": "Marquardt",
        "email": "Juana.Marquardt@gmail.com",
        "phone": "+1 811724-1399"
    },
    {
        "id": 81,
        "firstName": "Stacey",
        "lastName": "Daugherty",
        "email": "Stacey_Daugherty@hotmail.com",
        "phone": "+1 996787-8968"
    },
    {
        "id": 82,
        "firstName": "Gina",
        "lastName": "Hermann",
        "email": "Gina_Hermann8@gmail.com",
        "phone": "+1 616564-4801"
    },
    {
        "id": 83,
        "firstName": "Randall",
        "lastName": "Gerhold",
        "email": "Randall_Gerhold@gmail.com",
        "phone": "+1 863200-1218"
    },
    {
        "id": 84,
        "firstName": "Tyler",
        "lastName": "Runolfsdottir",
        "email": "Tyler.Runolfsdottir@gmail.com",
        "phone": "+1 876206-9570"
    },
    {
        "id": 85,
        "firstName": "Blanche",
        "lastName": "Rippin",
        "email": "Blanche.Rippin32@hotmail.com",
        "phone": "+1 438763-8325"
    },
    {
        "id": 86,
        "firstName": "Juana",
        "lastName": "Murazik",
        "email": "Juana_Murazik@gmail.com",
        "phone": "+1 458139-9042"
    },
    {
        "id": 87,
        "firstName": "Pedro",
        "lastName": "Altenwerth",
        "email": "Pedro_Altenwerth50@yahoo.com",
        "phone": "+1 375229-7891"
    },
    {
        "id": 88,
        "firstName": "Deborah",
        "lastName": "Green",
        "email": "Deborah16@yahoo.com",
        "phone": "+1 461671-8991"
    },
    {
        "id": 89,
        "firstName": "Greg",
        "lastName": "Torphy",
        "email": "Greg_Torphy0@yahoo.com",
        "phone": "+1 733876-3119"
    },
    {
        "id": 90,
        "firstName": "Pablo",
        "lastName": "Thiel",
        "email": "Pablo_Thiel82@hotmail.com",
        "phone": "+1 570002-1170"
    },
    {
        "id": 91,
        "firstName": "Renee",
        "lastName": "Swift",
        "email": "Renee88@yahoo.com",
        "phone": "+1 691048-5180"
    },
    {
        "id": 92,
        "firstName": "Henry",
        "lastName": "Pouros",
        "email": "Henry74@yahoo.com",
        "phone": "+1 662055-3312"
    },
    {
        "id": 93,
        "firstName": "Jason",
        "lastName": "Ankunding-Dickens",
        "email": "Jason.Ankunding-Dickens@gmail.com",
        "phone": "+1 303529-4713"
    },
    {
        "id": 94,
        "firstName": "Kenny",
        "lastName": "Koss",
        "email": "Kenny.Koss@yahoo.com",
        "phone": "+1 634007-4183"
    },
    {
        "id": 95,
        "firstName": "Kristie",
        "lastName": "Hills",
        "email": "Kristie.Hills77@yahoo.com",
        "phone": "+1 039148-1278"
    },
    {
        "id": 96,
        "firstName": "Travis",
        "lastName": "Conn",
        "email": "Travis.Conn4@gmail.com",
        "phone": "+1 965962-4870"
    },
    {
        "id": 97,
        "firstName": "Hattie",
        "lastName": "Lehner",
        "email": "Hattie.Lehner76@yahoo.com",
        "phone": "+1 068127-0665"
    },
    {
        "id": 98,
        "firstName": "Jonathon",
        "lastName": "Okuneva",
        "email": "Jonathon.Okuneva@gmail.com",
        "phone": "+1 732468-8541"
    },
    {
        "id": 99,
        "firstName": "Elijah",
        "lastName": "Parker",
        "email": "Elijah8@hotmail.com",
        "phone": "+1 856215-5013"
    },
    {
        "id": 100,
        "firstName": "Susie",
        "lastName": "Borer",
        "email": "Susie57@yahoo.com",
        "phone": "+1 450567-2844"
    },
    {
        "id": 101,
        "firstName": "Daryl",
        "lastName": "Price",
        "email": "Daryl_Price@yahoo.com",
        "phone": "+1 717126-9198"
    },
    {
        "id": 102,
        "firstName": "Bernard",
        "lastName": "Gerhold",
        "email": "Bernard.Gerhold@yahoo.com",
        "phone": "+1 801949-9885"
    },
    {
        "id": 103,
        "firstName": "Monique",
        "lastName": "Jakubowski",
        "email": "Monique63@gmail.com",
        "phone": "+1 563412-8952"
    },
    {
        "id": 104,
        "firstName": "Clint",
        "lastName": "Marvin",
        "email": "Clint_Marvin@yahoo.com",
        "phone": "+1 279976-8996"
    },
    {
        "id": 105,
        "firstName": "Alfredo",
        "lastName": "Fahey",
        "email": "Alfredo.Fahey@yahoo.com",
        "phone": "+1 942612-4998"
    },
    {
        "id": 106,
        "firstName": "Geoffrey",
        "lastName": "Botsford",
        "email": "Geoffrey34@gmail.com",
        "phone": "+1 941876-9199"
    },
    {
        "id": 107,
        "firstName": "Lorene",
        "lastName": "Leannon",
        "email": "Lorene_Leannon@yahoo.com",
        "phone": "+1 554649-2088"
    },
    {
        "id": 108,
        "firstName": "Cecelia",
        "lastName": "Bartoletti",
        "email": "Cecelia_Bartoletti59@yahoo.com",
        "phone": "+1 011595-7529"
    },
    {
        "id": 109,
        "firstName": "Victoria",
        "lastName": "Crona",
        "email": "Victoria88@hotmail.com",
        "phone": "+1 743737-2561"
    },
    {
        "id": 110,
        "firstName": "Jimmie",
        "lastName": "Kunze",
        "email": "Jimmie_Kunze76@hotmail.com",
        "phone": "+1 920912-8627"
    },
    {
        "id": 111,
        "firstName": "Amber",
        "lastName": "Herzog",
        "email": "Amber_Herzog77@gmail.com",
        "phone": "+1 950663-3181"
    },
    {
        "id": 112,
        "firstName": "Ryan",
        "lastName": "Corwin",
        "email": "Ryan_Corwin@gmail.com",
        "phone": "+1 696423-8467"
    },
    {
        "id": 113,
        "firstName": "Clarence",
        "lastName": "Powlowski",
        "email": "Clarence32@gmail.com",
        "phone": "+1 404446-4495"
    },
    {
        "id": 114,
        "firstName": "Drew",
        "lastName": "Abbott",
        "email": "Drew87@gmail.com",
        "phone": "+1 526707-0366"
    },
    {
        "id": 115,
        "firstName": "Frankie",
        "lastName": "Heaney",
        "email": "Frankie15@gmail.com",
        "phone": "+1 722739-3658"
    },
    {
        "id": 116,
        "firstName": "Clinton",
        "lastName": "Pollich",
        "email": "Clinton1@hotmail.com",
        "phone": "+1 968395-3514"
    },
    {
        "id": 117,
        "firstName": "Mike",
        "lastName": "Leffler",
        "email": "Mike15@yahoo.com",
        "phone": "+1 654460-1334"
    },
    {
        "id": 118,
        "firstName": "Candice",
        "lastName": "Schuster",
        "email": "Candice26@yahoo.com",
        "phone": "+1 724149-3686"
    },
    {
        "id": 119,
        "firstName": "Nathan",
        "lastName": "Feil",
        "email": "Nathan_Feil65@gmail.com",
        "phone": "+1 015301-4036"
    },
    {
        "id": 120,
        "firstName": "Clarence",
        "lastName": "Dooley",
        "email": "Clarence99@yahoo.com",
        "phone": "+1 571432-3473"
    },
    {
        "id": 121,
        "firstName": "Bob",
        "lastName": "Tremblay",
        "email": "Bob.Tremblay42@yahoo.com",
        "phone": "+1 857164-1467"
    },
    {
        "id": 122,
        "firstName": "Jerry",
        "lastName": "Vandervort",
        "email": "Jerry73@yahoo.com",
        "phone": "+1 442837-1833"
    },
    {
        "id": 123,
        "firstName": "Christie",
        "lastName": "Roberts",
        "email": "Christie.Roberts9@hotmail.com",
        "phone": "+1 060547-9825"
    },
    {
        "id": 124,
        "firstName": "Velma",
        "lastName": "Hackett",
        "email": "Velma52@hotmail.com",
        "phone": "+1 751815-9457"
    },
    {
        "id": 125,
        "firstName": "Terrence",
        "lastName": "Breitenberg",
        "email": "Terrence_Breitenberg@yahoo.com",
        "phone": "+1 131945-5291"
    },
    {
        "id": 126,
        "firstName": "Tracy",
        "lastName": "Berge",
        "email": "Tracy38@yahoo.com",
        "phone": "+1 887443-8977"
    },
    {
        "id": 127,
        "firstName": "Rudy",
        "lastName": "Boyle",
        "email": "Rudy_Boyle67@gmail.com",
        "phone": "+1 342219-0258"
    },
    {
        "id": 128,
        "firstName": "Glen",
        "lastName": "Borer",
        "email": "Glen.Borer25@gmail.com",
        "phone": "+1 408721-4789"
    },
    {
        "id": 129,
        "firstName": "Tim",
        "lastName": "Halvorson",
        "email": "Tim67@gmail.com",
        "phone": "+1 049832-8373"
    },
    {
        "id": 130,
        "firstName": "Stephanie",
        "lastName": "Cummerata",
        "email": "Stephanie_Cummerata19@hotmail.com",
        "phone": "+1 896314-7859"
    },
    {
        "id": 131,
        "firstName": "Freda",
        "lastName": "Schuster",
        "email": "Freda.Schuster@gmail.com",
        "phone": "+1 181311-2561"
    },
    {
        "id": 132,
        "firstName": "Luis",
        "lastName": "Schamberger",
        "email": "Luis_Schamberger@yahoo.com",
        "phone": "+1 641829-1023"
    },
    {
        "id": 133,
        "firstName": "Gene",
        "lastName": "Heller",
        "email": "Gene_Heller@hotmail.com",
        "phone": "+1 444463-8934"
    },
    {
        "id": 134,
        "firstName": "Suzanne",
        "lastName": "Miller",
        "email": "Suzanne97@hotmail.com",
        "phone": "+1 267486-1322"
    },
    {
        "id": 135,
        "firstName": "Danielle",
        "lastName": "Wiegand-Gleason",
        "email": "Danielle.Wiegand-Gleason@yahoo.com",
        "phone": "+1 305905-3329"
    },
    {
        "id": 136,
        "firstName": "Jessie",
        "lastName": "Robel",
        "email": "Jessie_Robel4@yahoo.com",
        "phone": "+1 357489-4518"
    },
    {
        "id": 137,
        "firstName": "Randall",
        "lastName": "Kuphal",
        "email": "Randall50@gmail.com",
        "phone": "+1 526430-3363"
    },
    {
        "id": 138,
        "firstName": "Rick",
        "lastName": "Goodwin",
        "email": "Rick_Goodwin73@hotmail.com",
        "phone": "+1 157172-0873"
    },
    {
        "id": 139,
        "firstName": "Julius",
        "lastName": "Balistreri",
        "email": "Julius32@hotmail.com",
        "phone": "+1 798116-8788"
    },
    {
        "id": 140,
        "firstName": "Clayton",
        "lastName": "Dicki",
        "email": "Clayton.Dicki@gmail.com",
        "phone": "+1 597409-7546"
    },
    {
        "id": 141,
        "firstName": "Sandra",
        "lastName": "Green",
        "email": "Sandra.Green@hotmail.com",
        "phone": "+1 762587-8170"
    },
    {
        "id": 142,
        "firstName": "Willie",
        "lastName": "Rodriguez",
        "email": "Willie.Rodriguez50@hotmail.com",
        "phone": "+1 854470-1853"
    },
    {
        "id": 143,
        "firstName": "Omar",
        "lastName": "Conn",
        "email": "Omar_Conn99@gmail.com",
        "phone": "+1 120572-7313"
    },
    {
        "id": 144,
        "firstName": "Crystal",
        "lastName": "Herzog",
        "email": "Crystal_Herzog36@gmail.com",
        "phone": "+1 535105-0080"
    },
    {
        "id": 145,
        "firstName": "Gail",
        "lastName": "Leffler",
        "email": "Gail.Leffler@yahoo.com",
        "phone": "+1 503373-8124"
    },
    {
        "id": 146,
        "firstName": "Jon",
        "lastName": "Kunde",
        "email": "Jon_Kunde@yahoo.com",
        "phone": "+1 410269-0091"
    },
    {
        "id": 147,
        "firstName": "Eileen",
        "lastName": "Wiza",
        "email": "Eileen68@hotmail.com",
        "phone": "+1 852036-7444"
    },
    {
        "id": 148,
        "firstName": "Saul",
        "lastName": "Mohr",
        "email": "Saul.Mohr@gmail.com",
        "phone": "+1 121688-2620"
    },
    {
        "id": 149,
        "firstName": "Sylvester",
        "lastName": "Krajcik",
        "email": "Sylvester.Krajcik0@yahoo.com",
        "phone": "+1 409722-6452"
    },
    {
        "id": 150,
        "firstName": "Byron",
        "lastName": "Hand",
        "email": "Byron_Hand15@gmail.com",
        "phone": "+1 215296-9506"
    },
    {
        "id": 151,
        "firstName": "Dixie",
        "lastName": "Lubowitz",
        "email": "Dixie.Lubowitz17@gmail.com",
        "phone": "+1 959092-3333"
    },
    {
        "id": 152,
        "firstName": "Naomi",
        "lastName": "Trantow",
        "email": "Naomi.Trantow13@hotmail.com",
        "phone": "+1 809015-3591"
    },
    {
        "id": 153,
        "firstName": "Clint",
        "lastName": "Hauck",
        "email": "Clint.Hauck@hotmail.com",
        "phone": "+1 442287-7366"
    },
    {
        "id": 154,
        "firstName": "Hattie",
        "lastName": "Little",
        "email": "Hattie21@gmail.com",
        "phone": "+1 500866-7745"
    },
    {
        "id": 155,
        "firstName": "Felicia",
        "lastName": "Mayer",
        "email": "Felicia5@gmail.com",
        "phone": "+1 236855-8048"
    }
]